adamz/__init__.py
adamz/adamz.py
adamz/optimizer.py
adamz-0.1.0.dist-info/METADATA
adamz-0.1.0.dist-info/WHEEL
adamz-0.1.0.dist-info/licenses/LICENSE
adamz-0.1.0.dist-info/RECORD
