Metadata-Version: 2.3
Name: adamz
Version: 0.1.0
Summary: An enhanced Adam optimizer with overshoot and stagnation handling.
Project-URL: Homepage, https://github.com/zaznov/AdamZ
Project-URL: Issues, https://github.com/zaznov/AdamZ/issues
Author-email: Ilia Zaznov <izaznov@gmail.com>, Atta Badii <atta.badii@reading.ac.uk>, Julian Kunkel <julian.kunkel@gwdg.de>, Alfonso Dufour <a.dufour@icmacentre.ac.uk>
License: MIT
Keywords: adam,deep learning,machine learning,optimizer
Classifier: License :: OSI Approved :: MIT License
Classifier: Operating System :: OS Independent
Classifier: Programming Language :: Python :: 3
Requires-Python: >=3.9
